aditya_pypi-1.0.1.dist-info/DESCRIPTION.rst
aditya_pypi-1.0.1.dist-info/METADATA
aditya_pypi-1.0.1.dist-info/RECORD
aditya_pypi-1.0.1.dist-info/WHEEL
aditya_pypi-1.0.1.dist-info/entry_points.txt
aditya_pypi-1.0.1.dist-info/metadata.json
aditya_pypi-1.0.1.dist-info/top_level.txt
hello_pypi/cli.py
